ERLANG/BL.py
ERLANG/CHAT.py
ERLANG/X.py
ERLANG/__init__.py
ERLANG/settings.py
erlangccmath-1.2.2.dist-info/licenses/LICENSE.txt
erlangccmath-1.2.2.dist-info/METADATA
erlangccmath-1.2.2.dist-info/WHEEL
erlangccmath-1.2.2.dist-info/top_level.txt
erlangccmath-1.2.2.dist-info/RECORD
